censo/__init__.py
censo/__main__.py
censo/__version__.py
censo/__version__.pyi
censo/ensemble.py
censo/logging.py
censo/molecules.py
censo/parallel.py
censo/params.py
censo/utilities.py
censo/assets/__init__.py
censo/assets/assets.py
censo/assets/dfa.json
censo/assets/hexadecane_25.pot
censo/assets/octanol_25.pot
censo/assets/solvents.json
censo/assets/solvents_new.json
censo/assets/wet-octanol_25.pot
censo/cli/__init__.py
censo/cli/cml_parser.py
censo/cli/interface.py
censo/config/__init__.py
censo/config/generic.py
censo/config/job_config.py
censo/config/parts_config.py
censo/config/paths.py
censo/config/setup.py
censo/config/parts/__init__.py
censo/config/parts/base.py
censo/config/parts/general.py
censo/config/parts/nmr.py
censo/config/parts/optimization.py
censo/config/parts/prescreening.py
censo/config/parts/refinement.py
censo/config/parts/rot.py
censo/config/parts/screening.py
censo/config/parts/uvvis.py
censo/ensembleopt/__init__.py
censo/ensembleopt/optimization.py
censo/ensembleopt/prescreening.py
censo/ensembleopt/refinement.py
censo/ensembleopt/screening.py
censo/processing/__init__.py
censo/processing/job.py
censo/processing/orca_processor.py
censo/processing/processor.py
censo/processing/qm_processor.py
censo/processing/results.py
censo/processing/tm_processor.py
censo/processing/xtb_processor.py
censo/properties/__init__.py
censo/properties/nmr.py
censo/properties/rot.py
censo/properties/uvvis.py
censo/scripts/__init__.py
censo/scripts/c2anmr.py
censo/scripts/nmrplot.py
censo/scripts/uvvisplot.py
censo-3.0.2.dist-info/licenses/COPYING
censo-3.0.2.dist-info/licenses/COPYING.LESSER
censo-3.0.2.dist-info/METADATA
censo-3.0.2.dist-info/WHEEL
censo-3.0.2.dist-info/entry_points.txt
censo-3.0.2.dist-info/top_level.txt
censo-3.0.2.dist-info/RECORD
