Metadata-Version: 2.4
Name: censo
Version: 3.0.2
Project-URL: homepage, https://github.com/grimme-lab/CENSO
Project-URL: documentation, https://xtb-docs.readthedocs.io/en/latest/CENSO_docs/censo.html
Requires-Python: >=3.12
License-File: COPYING
License-File: COPYING.LESSER
Requires-Dist: tabulate
Requires-Dist: pydantic
Requires-Dist: dask
Requires-Dist: distributed
Provides-Extra: scripts
Requires-Dist: numpy; extra == "scripts"
Requires-Dist: matplotlib; extra == "scripts"
Requires-Dist: pandas; extra == "scripts"
Provides-Extra: dev
Requires-Dist: pytest; extra == "dev"
Requires-Dist: tox; extra == "dev"
Requires-Dist: mypy; extra == "dev"
Requires-Dist: ruff; extra == "dev"
Requires-Dist: black; extra == "dev"
Requires-Dist: pre-commit; extra == "dev"
Requires-Dist: types-tabulate; extra == "dev"
Requires-Dist: pandas-stubs; extra == "dev"
Dynamic: license-file
